picrypt/__init__.py
picrypt-1.0.3.dist-info/METADATA
picrypt-1.0.3.dist-info/WHEEL
picrypt-1.0.3.dist-info/top_level.txt
picrypt-1.0.3.dist-info/RECORD
