Metadata-Version: 2.1
Name: picrypt
Version: 1.0.3
Summary: Simple cryptography
Home-page: UNKNOWN
Author: mi66mc
Author-email: miguelmalgarezi@gmail.com
License: MIT
Keywords: cryptography
Platform: UNKNOWN
Classifier: Development Status :: 5 - Production/Stable
Classifier: Intended Audience :: Education
Classifier: Operating System :: Microsoft :: Windows :: Windows 10
Classifier: License :: OSI Approved :: MIT License
Classifier: Programming Language :: Python :: 3
Requires-Dist: secrets
Requires-Dist: string
